{
  "input_parameters": {
    "input_json": "C:\\Users\\xinto\\Documents\\ecephys_spike_sorting\\CY_json\\CY18_LMD_20220207_imec0-input.json",
    "ks_postprocessing_params": {
      "deletion_mode": "lowAmpCluster",
      "remove_duplicates": true,
      "within_unit_overlap_window": 0.000333,
      "between_unit_overlap_window": 0.000333,
      "include_pcs": true,
      "align_avg_waveform": false,
      "cWaves_path": "C:\\Users\\xinto\\Documents\\C_Waves-win",
      "between_unit_dist_um": 42
    },
    "output_json": "C:\\Users\\xinto\\Documents\\ecephys_spike_sorting\\CY_json\\CY18_LMD_20220207_imec0-kilosort_postprocessing-output.json",
    "log_level": "ERROR",
    "directories": {
      "kilosort_output_directory": "E:\\ecephys_out\\catgt_CY18_LMD_20220207_g0\\CY18_LMD_20220207_g0_imec0\\imec0_ks2",
      "ecephys_directory": "C:\\Users\\xinto\\Documents\\ecephys_spike_sorting\\ecephys_spike_sorting",
      "npx_directory": "C:\\Users\\xinto\\Desktop",
      "kilosort_output_tmp": "D:\\kilosort_datatemp",
      "extracted_data_directory": "E:\\ecephys_out\\catgt_CY18_LMD_20220207_g0\\CY18_LMD_20220207_g0_imec0"
    },
    "ephys_params": {
      "probe_type": "NP1",
      "template_zero_padding": 21,
      "cluster_group_file_name": "cluster_group.tsv",
      "reorder_lfp_channels": false,
      "sample_rate": 30000.196653,
      "num_channels": 385,
      "vertical_site_spacing": 1e-05,
      "bit_volts": 2.34375,
      "lfp_band_file": "E:\\ecephys_out\\catgt_CY18_LMD_20220207_g0\\CY18_LMD_20220207_g0_imec0\\CY18_LMD_20220207_g0_tcat.imec0.lf.bin",
      "reference_channels": [
        191
      ],
      "ap_band_file": "E:\\ecephys_out\\catgt_CY18_LMD_20220207_g0\\CY18_LMD_20220207_g0_imec0\\CY18_LMD_20220207_g0_tcat.imec0.ap.bin",
      "lfp_sample_rate": 2500.0
    }
  },
  "execution_time": 413.6620533466339
}