{
  "input_parameters": {
    "cluster_metrics": {
      "cluster_metrics_file": "Z:\\HarveyLab\\Tier1\\Cindy\\ProcessedEphys\\CY\\25\\220528\\161024\\catgt_CY25_LMD_20220528_g0\\CY25_LMD_20220528_g0_imec0\\imec0_ks2\\metrics.csv"
    },
    "input_json": "C:\\Users\\xinto\\Documents\\ecephys_spike_sorting\\CY_json\\CY25_LMD_20220528_imec0-input.json",
    "ephys_params": {
      "ap_band_file": "Z:\\HarveyLab\\Tier1\\Cindy\\ProcessedEphys\\CY\\25\\220528\\161024\\catgt_CY25_LMD_20220528_g0\\CY25_LMD_20220528_g0_imec0\\CY25_LMD_20220528_g0_tcat.imec0.ap.bin",
      "vertical_site_spacing": 1e-05,
      "cluster_group_file_name": "cluster_group.tsv",
      "template_zero_padding": 21,
      "reference_channels": [
        191
      ],
      "reorder_lfp_channels": false,
      "bit_volts": 2.34375,
      "lfp_sample_rate": 2500.0,
      "sample_rate": 30000.189121,
      "lfp_band_file": "Z:\\HarveyLab\\Tier1\\Cindy\\ProcessedEphys\\CY\\25\\220528\\161024\\catgt_CY25_LMD_20220528_g0\\CY25_LMD_20220528_g0_imec0\\CY25_LMD_20220528_g0_tcat.imec0.lf.bin",
      "num_channels": 385,
      "probe_type": "NP1"
    },
    "waveform_metrics": {
      "waveform_metrics_file": "Z:\\HarveyLab\\Tier1\\Cindy\\ProcessedEphys\\CY\\25\\220528\\161024\\catgt_CY25_LMD_20220528_g0\\CY25_LMD_20220528_g0_imec0\\imec0_ks2\\waveform_metrics.csv"
    },
    "quality_metrics_params": {
      "tbin_sec": 0.001,
      "isi_threshold": 0.001,
      "drift_metrics_interval_s": 51.0,
      "n_silhouette": 10000,
      "n_neighbors": 4,
      "drift_metrics_min_spikes_per_interval": 10,
      "min_isi": 0.000166,
      "max_radius_um": 68,
      "include_pcs": true,
      "max_spikes_for_unit": 500,
      "max_spikes_for_nn": 10000
    },
    "log_level": "ERROR",
    "output_json": "C:\\Users\\xinto\\Documents\\ecephys_spike_sorting\\CY_json\\CY25_LMD_20220528_imec0-quality_metrics-output.json",
    "directories": {
      "ecephys_directory": "C:\\Users\\xinto\\Documents\\ecephys_spike_sorting\\ecephys_spike_sorting",
      "extracted_data_directory": "Z:\\HarveyLab\\Tier1\\Cindy\\ProcessedEphys\\CY\\25\\220528\\161024\\catgt_CY25_LMD_20220528_g0\\CY25_LMD_20220528_g0_imec0",
      "kilosort_output_tmp": "F:\\kilosort_datatemp",
      "kilosort_output_directory": "Z:\\HarveyLab\\Tier1\\Cindy\\ProcessedEphys\\CY\\25\\220528\\161024\\catgt_CY25_LMD_20220528_g0\\CY25_LMD_20220528_g0_imec0\\imec0_ks2",
      "npx_directory": "\\\\research.files.med.Harvard.edu\\neurobio\\HarveyLab\\Tier1\\Cindy\\EphysData\\CY\\25\\220528\\161024"
    }
  },
  "quality_metrics_output_file": "Z:\\HarveyLab\\Tier1\\Cindy\\ProcessedEphys\\CY\\25\\220528\\161024\\catgt_CY25_LMD_20220528_g0\\CY25_LMD_20220528_g0_imec0\\imec0_ks2\\metrics.csv",
  "execution_time": 1065.4831748008728
}